amocrm_client/__init__.py
amocrm_client/amocrm_client.py
amocrm_client/internal/__init__.py
amocrm_client/internal/amo/__init__.py
amocrm_client/internal/amo/amo.py
amocrm_client/internal/amo/internal/__init__.py
amocrm_client/internal/amo/internal/entities/__init__.py
amocrm_client/internal/amo/internal/entities/account.py
amocrm_client/internal/amo/internal/entities/catalog.py
amocrm_client/internal/amo/internal/entities/company.py
amocrm_client/internal/amo/internal/entities/contact.py
amocrm_client/internal/amo/internal/entities/customer.py
amocrm_client/internal/amo/internal/entities/entity.py
amocrm_client/internal/amo/internal/entities/lead.py
amocrm_client/internal/amo/internal/entities/pipeline.py
amocrm_client/internal/entities/__init__.py
amocrm_client/internal/entities/contact.py
amocrm_client/internal/entities/custom_field.py
amocrm_client/internal/entities/customer.py
amocrm_client/internal/entities/entity.py
amocrm_client/internal/entities/lead.py
amocrm_client/internal/entities/pipeline.py
amocrm_client/internal/entities/product.py
amocrm_client-0.2.5.dist-info/WHEEL
amocrm_client-0.2.5.dist-info/METADATA
amocrm_client-0.2.5.dist-info/RECORD
