Metadata-Version: 2.1
Name: amocrm-client
Version: 0.2.5
Summary: 
Author: BB Team
Requires-Python: >=3.9,<4.0
Classifier: Programming Language :: Python :: 3
Classifier: Programming Language :: Python :: 3.9
Classifier: Programming Language :: Python :: 3.10
Requires-Dist: aiohttp (==3.7.4)
Requires-Dist: httpx (>=0.21,<0.22)
